mynumpyshuffler/__init__.py
mynumpyshuffler/mynumpyshuffler.py
tests/__init__.py
tests/test_numpyshuffler.py
mynumpyshufflerupload-0.1.dist-info/License.txt
mynumpyshufflerupload-0.1.dist-info/METADATA
mynumpyshufflerupload-0.1.dist-info/WHEEL
mynumpyshufflerupload-0.1.dist-info/top_level.txt
mynumpyshufflerupload-0.1.dist-info/RECORD
