Metadata-Version: 2.1
Name: mynumpyshufflerupload
Version: 0.1
Summary: A Python library for shuffling NumPy arrays
Home-page: UNKNOWN
Author: osman.y
Author-email: osman.y@rapidlabs.ai
License: MIT
Platform: UNKNOWN
License-File: License.txt
Requires-Dist: numpy
